processor_ahuin/__init__.py
processor_ahuin/processor_ahuin.py
Processor_ahuin-0.1.2.dist-info/LICENSE
Processor_ahuin-0.1.2.dist-info/METADATA
Processor_ahuin-0.1.2.dist-info/WHEEL
Processor_ahuin-0.1.2.dist-info/top_level.txt
Processor_ahuin-0.1.2.dist-info/RECORD
