Metadata-Version: 2.1
Name: Processor-ahuin
Version: 0.1.2
Summary: 从JSON文件提取数据并保存到CSV文件的工具
Home-page: https://github.com/hui121315/DataProcessor.git
Author: ahuin
Author-email: z1156273305@gmail.com
Classifier: Programming Language :: Python :: 3
Classifier: License :: OSI Approved :: MIT License
Classifier: Operating System :: OS Independent
Requires-Python: >=3.6
License-File: LICENSE
Requires-Dist: pandas (>=1.1.5)
